{
  "servlets": [
    "com.paypal.selion.grid.servlets.LoginServlet",
    "com.paypal.selion.grid.servlets.ListAllNodes",
    "com.paypal.selion.grid.servlets.SauceServlet",
    "com.paypal.selion.grid.servlets.PasswordChangeServlet",
    "com.paypal.selion.grid.servlets.SauceConfigChangeServlet"
  ],
  "withoutServlets": [
    "org.openqa.grid.web.servlet.LifecycleServlet",
    "org.openqa.grid.web.servlet.Grid1HeartbeatServlet"
  ],
  "browserTimeout": 180000,
  "newSessionWaitTimeout": 1800000,
  "capabilityMatcher": "com.paypal.selion.grid.matchers.SeLionSauceCapabilityMatcher"
}
